setup.py
func_timedelta/__init__.py
func_timedelta/timer.py
func_timedelta.egg-info/PKG-INFO
func_timedelta.egg-info/SOURCES.txt
func_timedelta.egg-info/dependency_links.txt
func_timedelta.egg-info/top_level.txt