Metadata-Version: 2.1
Name: func-timedelta
Version: 0.1.0
Summary: 统计函数的执行耗时
Home-page: UNKNOWN
Author: wangcheng
Author-email: 154443603@qq.com
License: UNKNOWN
Platform: UNKNOWN
Classifier: Programming Language :: Python :: 3
Classifier: License :: OSI Approved :: MIT License
Classifier: Operating System :: OS Independent
Requires-Python: >=3.9
